.DS_Store
web_logs/__init__.py
web_logs/web_logs.py
web_logs/weblogs.py
weblogs/.DS_Store
weblogs/__init__.py
weblogs/web_logs.py
weblogs/weblogs.py
weblogs/data/app.py
weblogs/data/index.html
weblogs/data/json_path.txt
weblogs/data/style.css
weblogs-1.1.8.dist-info/LICENSE
weblogs-1.1.8.dist-info/METADATA
weblogs-1.1.8.dist-info/WHEEL
weblogs-1.1.8.dist-info/entry_points.txt
weblogs-1.1.8.dist-info/top_level.txt
weblogs-1.1.8.dist-info/RECORD
