Metadata-Version: 2.1
Name: weblogs
Version: 1.1.8
Summary: A Python Package to view stream of logs
Home-page: https://github.com/nishantsethi/web-logs
Author: Nishant Sethi
Author-email: sethi.nishant43@gmail.com
License: MIT
Keywords: python web-logs logs browser logs-stream
Platform: UNKNOWN
Classifier: Programming Language :: Python :: 3
Classifier: License :: OSI Approved :: MIT License
Classifier: Operating System :: OS Independent
Requires-Dist: Flask (==1.0.2)
